{
  "$p_1$": [
    "$k_46$"
  ],
  "$p_2$": [
    "$k_27$"
  ],
  "$p_3$": [
    "$k_82$"
  ],
  "$p_4$": [
    "$k_18$"
  ],
  "$p_5$": [
    "$k_27$"
  ],
  "$p_6$": [
    "$k_114$"
  ],
  "$p_7$": [
    "$k_122$"
  ],
  "$p_8$": [
    "$k_116$"
  ],
  "$p_9$": [
    "$k_36$"
  ],
  "$p_10$": [
    "$k_97$"
  ],
  "$p_11$": [
    "$k_91$"
  ],
  "$p_12$": [
    "$k_87$"
  ],
  "$p_13$": [
    "$k_76$"
  ],
  "$p_14$": [
    "$k_114$"
  ],
  "$p_15$": [
    "$k_88$"
  ],
  "$p_16$": [
    "$k_34$"
  ],
  "$p_17$": [
    "$k_69$"
  ],
  "$p_18$": [
    "$k_97$"
  ],
  "$p_19$": [
    "$k_66$"
  ],
  "$p_20$": [
    "$k_8$"
  ],
  "$p_21$": [
    "$k_29$"
  ],
  "$p_22$": [
    "$k_124$"
  ],
  "$p_23$": [
    "$k_4$"
  ],
  "$p_24$": [
    "$k_33$"
  ],
  "$p_25$": [
    "$k_78$"
  ],
  "$p_26$": [
    "$k_77$"
  ],
  "$p_27$": [
    "$k_15$"
  ],
  "$p_28$": [
    "$k_93$"
  ],
  "$p_29$": [
    "$k_5$"
  ],
  "$p_30$": [
    "$k_15$"
  ],
  "$p_31$": [
    "$k_42$"
  ],
  "$p_32$": [
    "$k_17$"
  ],
  "$p_33$": [
    "$k_95$"
  ],
  "$p_34$": [
    "$k_65$"
  ],
  "$p_35$": [
    "$k_18$"
  ],
  "$p_36$": [
    "$k_34$"
  ],
  "$p_37$": [
    "$k_125$"
  ],
  "$p_38$": [
    "$k_117$"
  ],
  "$p_39$": [
    "$k_38$"
  ],
  "$p_40$": [
    "$k_44$"
  ],
  "$p_41$": [
    "$k_123$"
  ],
  "$p_42$": [
    "$k_92$"
  ],
  "$p_43$": [
    "$k_97$"
  ],
  "$p_44$": [
    "$k_56$"
  ],
  "$p_45$": [
    "$k_42$"
  ],
  "$p_46$": [
    "$k_32$"
  ],
  "$p_47$": [
    "$k_21$"
  ],
  "$p_48$": [
    "$k_5$"
  ],
  "$p_49$": [
    "$k_104$"
  ],
  "$p_50$": [
    "$k_70$"
  ],
  "$p_51$": [
    "$k_62$"
  ],
  "$p_52$": [
    "$k_82$"
  ],
  "$p_53$": [
    "$k_3$"
  ],
  "$p_54$": [
    "$k_114$"
  ],
  "$p_55$": [
    "$k_15$"
  ],
  "$p_56$": [
    "$k_72$"
  ],
  "$p_57$": [
    "$k_110$"
  ],
  "$p_58$": [
    "$k_91$"
  ],
  "$p_59$": [
    "$k_16$"
  ],
  "$p_60$": [
    "$k_70$"
  ],
  "$p_61$": [
    "$k_109$"
  ],
  "$p_62$": [
    "$k_43$"
  ],
  "$p_63$": [
    "$k_51$"
  ],
  "$p_64$": [
    "$k_63$"
  ],
  "$p_65$": [
    "$k_71$"
  ],
  "$p_66$": [
    "$k_88$"
  ],
  "$p_67$": [
    "$k_81$"
  ],
  "$p_68$": [
    "$k_65$"
  ],
  "$p_69$": [
    "$k_84$"
  ],
  "$p_70$": [
    "$k_64$"
  ],
  "$p_71$": [
    "$k_121$"
  ],
  "$p_72$": [
    "$k_98$"
  ],
  "$p_73$": [
    "$k_53$"
  ],
  "$p_74$": [
    "$k_121$"
  ],
  "$p_75$": [
    "$k_42$"
  ],
  "$p_76$": [
    "$k_61$"
  ],
  "$p_77$": [
    "$k_29$"
  ],
  "$p_78$": [
    "$k_31$"
  ],
  "$p_79$": [
    "$k_108$"
  ],
  "$p_80$": [
    "$k_24$"
  ],
  "$p_81$": [
    "$k_102$"
  ],
  "$p_82$": [
    "$k_37$"
  ],
  "$p_83$": [
    "$k_113$"
  ],
  "$p_84$": [
    "$k_76$"
  ],
  "$p_85$": [
    "$k_64$"
  ],
  "$p_86$": [
    "$k_54$"
  ],
  "$p_87$": [
    "$k_111$"
  ],
  "$p_88$": [
    "$k_11$"
  ],
  "$p_89$": [
    "$k_97$"
  ],
  "$p_90$": [
    "$k_25$"
  ],
  "$p_91$": [
    "$k_75$"
  ],
  "$p_92$": [
    "$k_28$"
  ],
  "$p_93$": [
    "$k_48$"
  ],
  "$p_94$": [
    "$k_65$"
  ],
  "$p_95$": [
    "$k_101$"
  ],
  "$p_96$": [
    "$k_16$"
  ],
  "$p_97$": [
    "$k_13$"
  ],
  "$p_98$": [
    "$k_54$"
  ],
  "$p_99$": [
    "$k_104$"
  ],
  "$p_100$": [
    "$k_52$"
  ],
  "$p_101$": [
    "$k_37$"
  ],
  "$p_102$": [
    "$k_14$"
  ],
  "$p_103$": [
    "$k_105$"
  ],
  "$p_104$": [
    "$k_74$"
  ],
  "$p_105$": [
    "$k_55$"
  ],
  "$p_106$": [
    "$k_105$"
  ],
  "$p_107$": [
    "$k_83$"
  ],
  "$p_108$": [
    "$k_36$"
  ],
  "$p_109$": [
    "$k_16$"
  ],
  "$p_110$": [
    "$k_117$"
  ],
  "$p_111$": [
    "$k_122$"
  ],
  "$p_112$": [
    "$k_123$"
  ],
  "$p_113$": [
    "$k_27$"
  ],
  "$p_114$": [
    "$k_17$"
  ],
  "$p_115$": [
    "$k_32$"
  ],
  "$p_116$": [
    "$k_61$"
  ],
  "$p_117$": [
    "$k_85$"
  ],
  "$p_118$": [
    "$k_94$"
  ],
  "$p_119$": [
    "$k_6$"
  ],
  "$p_120$": [
    "$k_108$"
  ],
  "$p_121$": [
    "$k_114$"
  ],
  "$p_122$": [
    "$k_122$"
  ],
  "$p_123$": [
    "$k_70$"
  ],
  "$p_124$": [
    "$k_80$"
  ],
  "$p_125$": [
    "$k_60$"
  ],
  "$p_126$": [
    "$k_124$"
  ],
  "$p_127$": [
    "$k_16$"
  ],
  "$p_128$": [
    "$k_21$"
  ],
  "$p_129$": [
    "$k_15$"
  ],
  "$p_130$": [
    "$k_49$"
  ],
  "$p_131$": [
    "$k_38$"
  ],
  "$p_132$": [
    "$k_89$"
  ],
  "$p_133$": [
    "$k_106$"
  ],
  "$p_134$": [
    "$k_120$"
  ],
  "$p_135$": [
    "$k_85$"
  ],
  "$p_136$": [
    "$k_26$"
  ],
  "$p_137$": [
    "$k_65$"
  ],
  "$p_138$": [
    "$k_49$"
  ],
  "$p_139$": [
    "$k_72$"
  ],
  "$p_140$": [
    "$k_106$"
  ],
  "$p_141$": [
    "$k_77$"
  ],
  "$p_142$": [
    "$k_91$"
  ],
  "$p_143$": [
    "$k_121$"
  ],
  "$p_144$": [
    "$k_112$"
  ],
  "$p_145$": [
    "$k_119$"
  ],
  "$p_146$": [
    "$k_89$"
  ],
  "$p_147$": [
    "$k_11$"
  ],
  "$p_148$": [
    "$k_109$"
  ],
  "$p_149$": [
    "$k_16$"
  ],
  "$p_150$": [
    "$k_30$"
  ],
  "$p_151$": [
    "$k_125$"
  ],
  "$p_152$": [
    "$k_8$"
  ],
  "$p_153$": [
    "$k_30$"
  ],
  "$p_154$": [
    "$k_62$"
  ],
  "$p_155$": [
    "$k_100$"
  ],
  "$p_156$": [
    "$k_70$"
  ],
  "$p_157$": [
    "$k_120$"
  ],
  "$p_158$": [
    "$k_33$"
  ],
  "$p_159$": [
    "$k_49$"
  ],
  "$p_160$": [
    "$k_74$"
  ],
  "$p_161$": [
    "$k_49$"
  ],
  "$p_162$": [
    "$k_18$"
  ],
  "$p_163$": [
    "$k_66$"
  ],
  "$p_164$": [
    "$k_32$"
  ],
  "$p_165$": [
    "$k_123$"
  ],
  "$p_166$": [
    "$k_29$"
  ],
  "$p_167$": [
    "$k_64$"
  ],
  "$p_168$": [
    "$k_58$"
  ],
  "$p_169$": [
    "$k_21$"
  ],
  "$p_170$": [
    "$k_87$"
  ],
  "$p_171$": [
    "$k_68$"
  ],
  "$p_172$": [
    "$k_40$"
  ],
  "$p_173$": [
    "$k_105$"
  ],
  "$p_174$": [
    "$k_47$"
  ],
  "$p_175$": [
    "$k_108$"
  ],
  "$p_176$": [
    "$k_106$"
  ],
  "$p_177$": [
    "$k_115$"
  ],
  "$p_178$": [
    "$k_56$"
  ],
  "$p_179$": [
    "$k_42$"
  ],
  "$p_180$": [
    "$k_42$"
  ],
  "$p_181$": [
    "$k_11$"
  ],
  "$p_182$": [
    "$k_22$"
  ],
  "$p_183$": [
    "$k_123$"
  ],
  "$p_184$": [
    "$k_122$"
  ],
  "$p_185$": [
    "$k_15$"
  ],
  "$p_186$": [
    "$k_4$"
  ],
  "$p_187$": [
    "$k_46$"
  ],
  "$p_188$": [
    "$k_34$"
  ],
  "$p_189$": [
    "$k_21$"
  ],
  "$p_190$": [
    "$k_67$"
  ],
  "$p_191$": [
    "$k_9$"
  ],
  "$p_192$": [
    "$k_1$"
  ],
  "$p_193$": [
    "$k_88$"
  ],
  "$p_194$": [
    "$k_104$"
  ],
  "$p_195$": [
    "$k_74$"
  ],
  "$p_196$": [
    "$k_114$"
  ],
  "$p_197$": [
    "$k_74$"
  ],
  "$p_198$": [
    "$k_19$"
  ],
  "$p_199$": [
    "$k_64$"
  ],
  "$p_200$": [
    "$k_29$"
  ],
  "$p_201$": [
    "$k_13$"
  ],
  "$p_202$": [
    "$k_63$"
  ],
  "$p_203$": [
    "$k_57$"
  ],
  "$p_204$": [
    "$k_19$"
  ],
  "$p_205$": [
    "$k_102$"
  ],
  "$p_206$": [
    "$k_16$"
  ],
  "$p_207$": [
    "$k_62$"
  ],
  "$p_208$": [
    "$k_120$"
  ],
  "$p_209$": [
    "$k_54$"
  ],
  "$p_210$": [
    "$k_91$"
  ],
  "$p_211$": [
    "$k_16$"
  ],
  "$p_212$": [
    "$k_51$"
  ],
  "$p_213$": [
    "$k_39$"
  ],
  "$p_214$": [
    "$k_25$"
  ],
  "$p_215$": [
    "$k_107$"
  ],
  "$p_216$": [
    "$k_102$"
  ],
  "$p_217$": [
    "$k_44$"
  ],
  "$p_218$": [
    "$k_66$"
  ],
  "$p_219$": [
    "$k_104$"
  ],
  "$p_220$": [
    "$k_61$"
  ],
  "$p_221$": [
    "$k_99$"
  ],
  "$p_222$": [
    "$k_21$"
  ],
  "$p_223$": [
    "$k_30$"
  ],
  "$p_224$": [
    "$k_69$"
  ],
  "$p_225$": [
    "$k_16$"
  ],
  "$p_226$": [
    "$k_82$"
  ],
  "$p_227$": [
    "$k_77$"
  ],
  "$p_228$": [
    "$k_22$"
  ],
  "$p_229$": [
    "$k_77$"
  ],
  "$p_230$": [
    "$k_61$"
  ],
  "$p_231$": [
    "$k_79$"
  ],
  "$p_232$": [
    "$k_117$"
  ],
  "$p_233$": [
    "$k_12$"
  ],
  "$p_234$": [
    "$k_76$"
  ],
  "$p_235$": [
    "$k_51$"
  ],
  "$p_236$": [
    "$k_112$"
  ],
  "$p_237$": [
    "$k_100$"
  ],
  "$p_238$": [
    "$k_41$"
  ],
  "$p_239$": [
    "$k_125$"
  ],
  "$p_240$": [
    "$k_25$"
  ],
  "$p_241$": [
    "$k_55$"
  ],
  "$p_242$": [
    "$k_118$"
  ],
  "$p_243$": [
    "$k_102$"
  ],
  "$p_244$": [
    "$k_124$"
  ],
  "$p_245$": [
    "$k_117$"
  ],
  "$p_246$": [
    "$k_97$"
  ],
  "$p_247$": [
    "$k_32$"
  ],
  "$p_248$": [
    "$k_13$"
  ],
  "$p_249$": [
    "$k_61$"
  ],
  "$p_250$": [
    "$k_87$"
  ]
}